{
  "fold_count": 3,
  "fold_results_preview": [
    {
      "fold_number": 1,
      "pricing_mode": "candle_proxy",
      "selected_allow_no": false,
      "selected_max_price": 100.0,
      "selected_max_spread": 2.0,
      "selected_min_edge": 0.05,
      "selected_min_price": 0.0,
      "selected_min_samples": 1,
      "skip_reason": "",
      "test_average_edge_at_entry": 0.426606,
      "test_brier_score": 0.158036,
      "test_end": "2025-12-30",
      "test_hit_rate": 0.045455,
      "test_no_trades": 0,
      "test_rows_evaluated": 180,
      "test_start": "2025-12-16",
      "test_total_gross_pnl": 0.64,
      "test_total_net_pnl": 0.19,
      "test_trades": 44,
      "test_yes_trades": 44,
      "train_end": "2025-11-30",
      "train_start": "2025-11-01",
      "validation_average_net_pnl_per_trade": -0.028,
      "validation_end": "2025-12-15",
      "validation_start": "2025-12-01",
      "validation_total_net_pnl": -1.12,
      "validation_trades": 40
    },
    {
      "fold_number": 2,
      "pricing_mode": "candle_proxy",
      "selected_allow_no": false,
      "selected_max_price": 100.0,
      "selected_max_spread": 2.0,
      "selected_min_edge": 0.05,
      "selected_min_price": 0.0,
      "selected_min_samples": 1,
      "skip_reason": "",
      "test_average_edge_at_entry": 0.500766,
      "test_brier_score": 0.182701,
      "test_end": "2026-01-14",
      "test_hit_rate": 0.022222,
      "test_no_trades": 0,
      "test_rows_evaluated": 180,
      "test_start": "2025-12-31",
      "test_total_gross_pnl": -0.07,
      "test_total_net_pnl": -0.53,
      "test_trades": 45,
      "test_yes_trades": 45,
      "train_end": "2025-12-15",
      "train_start": "2025-11-01",
      "validation_average_net_pnl_per_trade": 0.004318,
      "validation_end": "2025-12-30",
      "validation_start": "2025-12-16",
      "validation_total_net_pnl": 0.19,
      "validation_trades": 44
    },
    {
      "fold_number": 3,
      "pricing_mode": "candle_proxy",
      "selected_allow_no": false,
      "selected_max_price": 100.0,
      "selected_max_spread": 2.0,
      "selected_min_edge": 0.05,
      "selected_min_price": 0.0,
      "selected_min_samples": 1,
      "skip_reason": "",
      "test_average_edge_at_entry": 0.539082,
      "test_brier_score": 0.194699,
      "test_end": "2026-01-29",
      "test_hit_rate": 0.0,
      "test_no_trades": 0,
      "test_rows_evaluated": 180,
      "test_start": "2026-01-15",
      "test_total_gross_pnl": -1.36,
      "test_total_net_pnl": -1.78,
      "test_trades": 41,
      "test_yes_trades": 41,
      "train_end": "2025-12-30",
      "train_start": "2025-11-01",
      "validation_average_net_pnl_per_trade": -0.011778,
      "validation_end": "2026-01-14",
      "validation_start": "2025-12-31",
      "validation_total_net_pnl": -0.53,
      "validation_trades": 45
    }
  ],
  "pricing_mode": "candle_proxy",
  "results_by_pricing_mode": {
    "candle_proxy": {
      "average_edge_at_entry": 0.48775,
      "average_gross_pnl_per_trade": -0.006077,
      "average_net_pnl_per_trade": -0.016308,
      "brier_score": 0.178479,
      "folds_attempted": 3,
      "folds_scored": 3,
      "hit_rate": 0.023077,
      "no_trades_taken": 0,
      "pricing_mode": "candle_proxy",
      "rows_evaluated": 540,
      "selected_thresholds_per_fold": [
        {
          "fold_number": 1,
          "selected_allow_no": false,
          "selected_max_price": 100.0,
          "selected_max_spread": 2.0,
          "selected_min_edge": 0.05,
          "selected_min_price": 0.0,
          "selected_min_samples": 1
        },
        {
          "fold_number": 2,
          "selected_allow_no": false,
          "selected_max_price": 100.0,
          "selected_max_spread": 2.0,
          "selected_min_edge": 0.05,
          "selected_min_price": 0.0,
          "selected_min_samples": 1
        },
        {
          "fold_number": 3,
          "selected_allow_no": false,
          "selected_max_price": 100.0,
          "selected_max_spread": 2.0,
          "selected_min_edge": 0.05,
          "selected_min_price": 0.0,
          "selected_min_samples": 1
        }
      ],
      "total_gross_pnl": -0.79,
      "total_net_pnl": -2.12,
      "trades_taken": 130,
      "yes_trades_taken": 130
    }
  },
  "rows_available": 540,
  "selection_config": {
    "min_trades_for_selection": 1,
    "selection_metric": "total_net_pnl"
  },
  "window_config": {
    "expanding": true,
    "step_window": 15,
    "test_window": 15,
    "train_window": 30,
    "validation_window": 15,
    "window_profile": "research_short"
  }
}
